Metadata-Version: 2.1
Name: miniga4py
Version: 5.7.0a3
Summary: miniga4py Minimal Python bindings for the Global Arrays Toolkit library
Home-page: https://github.com/GlobalArrays/ga4py
Author: Roberto Vidmar
Author-email: rvidmar@inogs.it
Maintainer: Roberto Vidmar
Maintainer-email: rvidmar@inogs.it
License: BSD
Download-URL: https://github.com/GlobalArrays/ga4py/tree/feature/py3
Keywords: miniga4py,MPI,GlobalArrays
Platform: POSIX
Classifier: Development Status :: 3 - Alpha
Classifier: Intended Audience :: Developers
Classifier: Intended Audience :: Science/Research
Classifier: License :: OSI Approved :: BSD License
Classifier: Operating System :: POSIX
Classifier: Programming Language :: C
Classifier: Programming Language :: C++
Classifier: Programming Language :: Fortran
Classifier: Programming Language :: Python
Classifier: Topic :: Scientific/Engineering
Classifier: Topic :: Software Development :: Libraries
